pkqer/__init__.py
pkqer/ngw.py
pkqer/bike/__init__.py
pkqer/bike/bike0.py
pkqer/bike/bike1.py
pkqer/bike/bike2.py
pkqer/bike/bike3.py
pkqer/bike/bike4.py
pkqer/bike/bike5.py
pkqer/bike/bike6.py
pkqer/bike/bike7.py
pkqer/internetloganalysis/__init__.py
pkqer/internetloganalysis/internetlogs/__init__.py
pkqer/internetloganalysis/internetlogs/browser.py
pkqer/internetloganalysis/internetlogs/ip.py
pkqer/internetloganalysis/internetlogs/pv.py
pkqer/internetloganalysis/internetlogs/time.py
pkqer/internetloganalysis/retrievelog/__init__.py
pkqer/internetloganalysis/retrievelog/behavior.py
pkqer/internetloganalysis/retrievelog/key.py
pkqer/internetloganalysis/retrievelog/rank.py
pkqer/internetloganalysis/retrievelog/time.py
pkqer/internetloganalysis/retrievelog/url.py
pkqer/internetloganalysis/retrievelog/userkey.py
pkqer/jichuhuanjing/__init__.py
pkqer/jichuhuanjing/bigdata.py
pkqer/luntan/__init__.py
pkqer/luntan/data.py
pkqer/luntan/lt_operator.py
pkqer/luntan/pazhong.py
pkqer/python_demo/__init__.py
pkqer/python_demo/damixiaoliang.py
pkqer/python_demo/ershoufang.py
pkqer/python_demo/jisuanjinggaimianji.py
pkqer/python_demo/jiujiu.py
pkqer/python_demo/sandiantu.py
pkqer/python_demo/wuliufenxi.py
pkqer/python_demo/xiaoshou.py
pkqer/python_demo/yichangdian.py
pkqer/python_demo/zuiyoucaigoufangan.py
pkqer/shangcheng/__init__.py
pkqer/shangcheng/sc_operator.py
pkqer/shangcheng/spider.py
pkqer/spark/Analysis.py
pkqer/spark/HadoopFileIoAdapter.py
pkqer/spark/NetCount1.py
pkqer/spark/NetCount2.py
pkqer/spark/NetCount3.py
pkqer/spark/NetCount4.py
pkqer/spark/NetCount5.py
pkqer/spark/NetCount6.py
pkqer/spark/UserUtils.py
pkqer/spark/WebLogAn.py
pkqer/spark/WordSegment.py
pkqer/spark/WordSegmentTDIDF.py
pkqer/spark/__init__.py
pkqer/spark/pom.py
pkqer/stream/__init__.py
pkqer/stream/main.py
pkqer-1.0.dist-info/LICENSE
pkqer-1.0.dist-info/METADATA
pkqer-1.0.dist-info/WHEEL
pkqer-1.0.dist-info/top_level.txt
pkqer-1.0.dist-info/RECORD
